lockllm/__init__.py
lockllm/async_client.py
lockllm/async_http_client.py
lockllm/async_scan.py
lockllm/client.py
lockllm/errors.py
lockllm/http_client.py
lockllm/py.typed
lockllm/scan.py
lockllm/utils.py
lockllm/types/__init__.py
lockllm/types/common.py
lockllm/types/providers.py
lockllm/types/scan.py
lockllm/wrappers/__init__.py
lockllm/wrappers/anthropic_wrapper.py
lockllm/wrappers/generic_wrapper.py
lockllm/wrappers/openai_wrapper.py
lockllm-1.0.0.dist-info/licenses/LICENSE
lockllm-1.0.0.dist-info/METADATA
lockllm-1.0.0.dist-info/WHEEL
lockllm-1.0.0.dist-info/top_level.txt
lockllm-1.0.0.dist-info/RECORD
