Metadata-Version: 2.4
Name: lockllm
Version: 1.0.0
Summary: Enterprise-grade AI security SDK with prompt injection detection for Python
Author-email: LockLLM <support@lockllm.com>
License: MIT
Project-URL: Homepage, https://www.lockllm.com
Project-URL: Documentation, https://www.lockllm.com/docs
Project-URL: Repository, https://github.com/lockllm/lockllm-pip
Project-URL: Issues, https://github.com/lockllm/lockllm-pip/issues
Project-URL: Changelog, https://github.com/lockllm/lockllm-pip/blob/main/CHANGELOG.md
Keywords: openai,anthropic,llm,ai,security,prompt-injection,jailbreak,ai-security
Classifier: Development Status :: 5 - Production/Stable
Classifier: Intended Audience :: Developers
Classifier: License :: OSI Approved :: MIT License
Classifier: Programming Language :: Python :: 3
Classifier: Programming Language :: Python :: 3.8
Classifier: Programming Language :: Python :: 3.9
Classifier: Programming Language :: Python :: 3.10
Classifier: Programming Language :: Python :: 3.11
Classifier: Programming Language :: Python :: 3.12
Classifier: Topic :: Security
Classifier: Topic :: Software Development :: Libraries :: Python Modules
Requires-Python: >=3.8
License-File: LICENSE
Requires-Dist: requests>=2.31.0
Requires-Dist: httpx>=0.24.0
Requires-Dist: typing-extensions>=4.5.0; python_version < "3.11"
Provides-Extra: dev
Requires-Dist: pytest>=7.0.0; extra == "dev"
Requires-Dist: pytest-cov>=4.0.0; extra == "dev"
Requires-Dist: pytest-mock>=3.10.0; extra == "dev"
Requires-Dist: pytest-asyncio>=0.21.0; extra == "dev"
Requires-Dist: mypy>=1.0.0; extra == "dev"
Requires-Dist: black>=23.0.0; extra == "dev"
Requires-Dist: isort>=5.12.0; extra == "dev"
Requires-Dist: flake8>=6.0.0; extra == "dev"
Requires-Dist: build>=0.10.0; extra == "dev"
Requires-Dist: twine>=4.0.0; extra == "dev"
Requires-Dist: openai>=1.0.0; extra == "dev"
Requires-Dist: anthropic>=0.18.0; extra == "dev"
Requires-Dist: cohere>=4.0.0; extra == "dev"
Dynamic: license-file
